bjutNet/__init__.py
bjutNet/__version__.py
bjutNet/bjutNet.py
bjutNet-1.0.1.dist-info/DESCRIPTION.rst
bjutNet-1.0.1.dist-info/METADATA
bjutNet-1.0.1.dist-info/RECORD
bjutNet-1.0.1.dist-info/WHEEL
bjutNet-1.0.1.dist-info/metadata.json
bjutNet-1.0.1.dist-info/top_level.txt
