Metadata-Version: 2.0
Name: bjutNet
Version: 1.0.1
Summary: 连接北工大校园网的SDK
Home-page: https://github.com/wangke0809/BJUT_Survival_Script
Author: wangke
Author-email: 772930093@qq.com
License: MIT
Platform: UNKNOWN
Classifier: License :: OSI Approved :: MIT License
Classifier: Programming Language :: Python
Classifier: Programming Language :: Python :: 2.6
Classifier: Programming Language :: Python :: 2.7
Classifier: Programming Language :: Python :: 3
Classifier: Programming Language :: Python :: 3.3
Classifier: Programming Language :: Python :: 3.4
Classifier: Programming Language :: Python :: 3.5
Classifier: Programming Language :: Python :: 3.6
Requires-Dist: pypiwin32
Requires-Dist: requests
